{"nodes": [{"layer": 3, "name": "Maize"}, {"layer": 5, "name": "Production", "fill": "#b5cf6b"}, {"layer": 3, "name": "Rye"}, {"layer": 3, "name": "Nuts"}, {"layer": 3, "name": "Barley"}, {"layer": 3, "name": "Tomatoes"}, {"layer": 3, "name": "Sunflower seed"}, {"layer": 3, "name": "Cereals, Other"}, {"layer": 3, "name": "Wheat"}, {"layer": 3, "name": "Treenuts"}, {"layer": 3, "name": "Vegetables, Other"}, {"layer": 3, "name": "Peas"}, {"layer": 3, "name": "Oilcrops, Other"}, {"layer": 3, "name": "Oats"}, {"layer": 3, "name": "Potatoes"}, {"layer": 3, "name": "Beans"}, {"layer": 3, "name": "Apples"}, {"layer": 3, "name": "Sugar beet"}, {"layer": 3, "name": "Fruits, Other"}, {"layer": 3, "name": "Rape and Mustardseed"}, {"layer": 3, "name": "Onions"}, {"layer": 3, "name": "Pulses, Other"}, {"layer": 1, "name": "Electricity", "fill": "#bcbd22"}, {"layer": 0, "name": "Fossil Fuels", "fill": "#c49c94"}, {"layer": 0, "name": "Renewables & Nuclear", "fill": "#2ca02c"}, {"layer": 1, "name": "Fertilizers", "fill": "#c5b0d5"}, {"layer": 0, "name": "Labor", "fill": "#7f7f7f"}], "links": [{"source": 0, "prod": 39.0, "target": 1, "value": 0.15767204731757145, "supply": [{"l": "Maize", "v": 0.15767204731757145}]}, {"source": 2, "prod": 1397.0, "target": 1, "value": 4.5521478307000578, "supply": [{"l": "Rye", "v": 4.5521478307000578}]}, {"source": 3, "prod": 18.0, "target": 1, "value": 0.058217371317257148, "supply": [{"l": "Nuts", "v": 0.058217371317257148}]}, {"source": 4, "prod": 2032.0, "target": 1, "value": 5.6332237388888826, "supply": [{"l": "Barley", "v": 5.6332237388888826}]}, {"source": 5, "prod": 230.0, "target": 1, "value": 0.045730858616697893, "supply": [{"l": "Tomatoes", "v": 0.045730858616697893}]}, {"source": 6, "prod": 20.0, "target": 1, "value": 0.14765275334086961, "supply": [{"l": "Sunflower seed", "v": 0.14765275334086961}]}, {"source": 7, "prod": 1236.0, "target": 1, "value": 3.553165185079775, "supply": [{"l": "Cereals, Other", "v": 3.553165185079775}]}, {"source": 8, "prod": 1121.0, "target": 1, "value": 3.7268626534063309, "supply": [{"l": "Wheat", "v": 3.7268626534063309}]}, {"source": 9, "prod": 18.0, "target": 1, "value": 0.059347805711766989, "supply": [{"l": "Treenuts", "v": 0.059347805711766989}]}, {"source": 10, "prod": 1656.0, "target": 1, "value": 0.52366473159569793, "supply": [{"l": "Vegetables, Other", "v": 0.52366473159569793}]}, {"source": 11, "prod": 110.0, "target": 1, "value": 0.050922682785499516, "supply": [{"l": "Peas", "v": 0.050922682785499516}]}, {"source": 12, "prod": 23.0, "target": 1, "value": 0.16980066634200003, "supply": [{"l": "Oilcrops, Other", "v": 0.16980066634200003}]}, {"source": 13, "prod": 765.0, "target": 1, "value": 1.8745820592340494, "supply": [{"l": "Oats", "v": 1.8745820592340494}]}, {"source": 14, "prod": 9902.0, "target": 1, "value": 7.7187112756920184, "supply": [{"l": "Potatoes", "v": 7.7187112756920184}]}, {"source": 15, "prod": 115.0, "target": 1, "value": 0.05323735018484041, "supply": [{"l": "Beans", "v": 0.05323735018484041}]}, {"source": 16, "prod": 232.0, "target": 1, "value": 0.12236388380217923, "supply": [{"l": "Apples", "v": 0.12236388380217923}]}, {"source": 17, "prod": 3088.0, "target": 1, "value": 3.5889422153600004, "supply": [{"l": "Sugar beet", "v": 3.5889422153600004}]}, {"source": 18, "prod": 126.0, "target": 1, "value": 0.062080451316852164, "supply": [{"l": "Fruits, Other", "v": 0.062080451316852164}]}, {"source": 19, "prod": 143.0, "target": 1, "value": 1.0557171863872175, "supply": [{"l": "Rape and Mustardseed", "v": 1.0557171863872175}]}, {"source": 20, "prod": 156.0, "target": 1, "value": 0.056325129904454443, "supply": [{"l": "Onions", "v": 0.056325129904454443}]}, {"source": 21, "prod": 200.0, "target": 1, "value": 0.092586695973635502, "supply": [{"l": "Pulses, Other", "v": 0.092586695973635502}]}, {"source": 22, "prod": 0, "target": 6, "value": 0.00026977178981337088, "supply": "[{\"l\":'Energy for power irrigation',\"v\":0.00026977178981337088}]"}, {"source": 22, "prod": 0, "target": 0, "value": 0.0016132353030839576, "supply": "[{\"l\":'Energy for power irrigation',\"v\":0.0016132353030839576}]"}, {"source": 22, "prod": 0, "target": 10, "value": 0.018020755559533176, "supply": "[{\"l\":'Energy for power irrigation',\"v\":0.018020755559533176}]"}, {"source": 22, "prod": 0, "target": 8, "value": 0.014529908599348156, "supply": "[{\"l\":'Energy for power irrigation',\"v\":0.014529908599348156}]"}, {"source": 22, "prod": 0, "target": 7, "value": 0.013585707335001357, "supply": "[{\"l\":'Energy for power irrigation',\"v\":0.013585707335001357}]"}, {"source": 22, "prod": 0, "target": 9, "value": 0.00021042199605442925, "supply": "[{\"l\":'Energy for power irrigation',\"v\":0.00021042199605442925}]"}, {"source": 22, "prod": 0, "target": 14, "value": 0.10729363624457386, "supply": "[{\"l\":'Energy for power irrigation',\"v\":0.10729363624457386}]"}, {"source": 22, "prod": 0, "target": 13, "value": 0.0082712030756779513, "supply": "[{\"l\":'Energy for power irrigation',\"v\":0.0082712030756779513}]"}, {"source": 22, "prod": 0, "target": 2, "value": 0.015091033922159967, "supply": "[{\"l\":'Energy for power irrigation',\"v\":0.015091033922159967}]"}, {"source": 22, "prod": 0, "target": 3, "value": 0.00021042199605442925, "supply": "[{\"l\":'Energy for power irrigation',\"v\":0.00021042199605442925}]"}, {"source": 22, "prod": 0, "target": 11, "value": 0.0012301593615489711, "supply": "[{\"l\":'Energy for power irrigation',\"v\":0.0012301593615489711}]"}, {"source": 22, "prod": 0, "target": 21, "value": 0.002158174318506967, "supply": "[{\"l\":'Energy for power irrigation',\"v\":0.002158174318506967}]"}, {"source": 22, "prod": 0, "target": 15, "value": 0.0012463456689377733, "supply": "[{\"l\":'Energy for power irrigation',\"v\":0.0012463456689377733}]"}, {"source": 22, "prod": 0, "target": 4, "value": 0.023362236997837918, "supply": "[{\"l\":'Energy for power irrigation',\"v\":0.023362236997837918}]"}, {"source": 22, "prod": 0, "target": 17, "value": 0.033322211477747568, "supply": "[{\"l\":'Energy for power irrigation',\"v\":0.033322211477747568}]"}, {"source": 22, "prod": 0, "target": 19, "value": 0.0015646763809175511, "supply": "[{\"l\":'Energy for power irrigation',\"v\":0.0015646763809175511}]"}, {"source": 22, "prod": 0, "target": 12, "value": 0.00026977178981337088, "supply": "[{\"l\":'Energy for power irrigation',\"v\":0.00026977178981337088}]"}, {"source": 22, "prod": 0, "target": 20, "value": 0.001758912069583178, "supply": "[{\"l\":'Energy for power irrigation',\"v\":0.001758912069583178}]"}, {"source": 22, "prod": 0, "target": 18, "value": 0.0016510033536578296, "supply": "[{\"l\":'Energy for power irrigation',\"v\":0.0016510033536578296}]"}, {"source": 22, "prod": 0, "target": 5, "value": 0.0027246950771150458, "supply": "[{\"l\":'Energy for power irrigation',\"v\":0.0027246950771150458}]"}, {"source": 22, "prod": 0, "target": 16, "value": 0.0033020067073156593, "supply": "[{\"l\":'Energy for power irrigation',\"v\":0.0033020067073156593}]"}, {"source": 23, "prod": 0, "target": 22, "value": 0.48824796428725581, "supply": [{"l": "Coal", "v": 0.0}, {"l": "Natural gas", "v": 0.45596529482426568}, {"l": "Oil", "v": 0.032282669462990125}]}, {"source": 24, "prod": 0, "target": 22, "value": 0.00027530830987579699, "supply": [{"l": "Nuclear", "v": 0.0}, {"l": "Hydroelectric", "v": 0.00026721100664415587}, {"l": "Renewable", "v": 8.0973032316410997e-06}]}, {"source": 23, "prod": 0, "target": 6, "value": 0.0082005042721389736, "supply": [{"l": "Motor Gasoline", "v": 0.00044668170864945654}, {"l": "Gas-Diesel oil", "v": 0.0073835045148356922}, {"l": "Natural gas (including LNG)", "v": 0.00033214945803172974}, {"l": "Fuel oil", "v": 1.1981105450430251e-05}, {"l": "Liquefied petroleum gas (LPG)", "v": 1.8536185156291995e-05}, {"l": "Coal", "v": 7.6513000153737741e-06}]}, {"source": 23, "prod": 0, "target": 0, "value": 0.049039015547391061, "supply": [{"l": "Motor Gasoline", "v": 0.0026711566177237498}, {"l": "Gas-Diesel oil", "v": 0.04415335699871744}, {"l": "Natural gas (including LNG)", "v": 0.0019862537590297439}, {"l": "Fuel oil", "v": 7.1647010593572894e-05}, {"l": "Liquefied petroleum gas (LPG)", "v": 0.00011084638723462614}, {"l": "Coal", "v": 4.5754774091935174e-05}]}, {"source": 23, "prod": 0, "target": 10, "value": 0.54779368537888351, "supply": [{"l": "Motor Gasoline", "v": 0.0298383381377837}, {"l": "Gas-Diesel oil", "v": 0.49321810159102425}, {"l": "Natural gas (including LNG)", "v": 0.022187583796519549}, {"l": "Fuel oil", "v": 0.00080033784408874088}, {"l": "Liquefied petroleum gas (LPG)", "v": 0.0012382171684403055}, {"l": "Coal", "v": 0.00051110684102696822}]}, {"source": 23, "prod": 0, "target": 8, "value": 0.44167916009740515, "supply": [{"l": "Motor Gasoline", "v": 0.024058276827859729}, {"l": "Gas-Diesel oil", "v": 0.3976755531690504}, {"l": "Natural gas (including LNG)", "v": 0.017889569809588963}, {"l": "Fuel oil", "v": 0.00064530233956017332}, {"l": "Liquefied petroleum gas (LPG)", "v": 0.00099835893251788688}, {"l": "Coal", "v": 0.0004120990188280315}]}, {"source": 23, "prod": 0, "target": 7, "value": 0.41297739514491871, "supply": [{"l": "Motor Gasoline", "v": 0.022494890847586629}, {"l": "Gas-Diesel oil", "v": 0.37183328736712545}, {"l": "Natural gas (including LNG)", "v": 0.01672704670647791}, {"l": "Fuel oil", "v": 0.00060336847048366739}, {"l": "Liquefied petroleum gas (LPG)", "v": 0.00093348228447086496}, {"l": "Coal", "v": 0.00038531946877422328}]}, {"source": 23, "prod": 0, "target": 9, "value": 0.0063963933322683996, "supply": [{"l": "Motor Gasoline", "v": 0.00034841173274657606}, {"l": "Gas-Diesel oil", "v": 0.0057591335215718392}, {"l": "Natural gas (including LNG)", "v": 0.0002590765772647492}, {"l": "Fuel oil", "v": 9.345262251335595e-06}, {"l": "Liquefied petroleum gas (LPG)", "v": 1.4458224421907757e-05}, {"l": "Coal", "v": 5.9680140119915439e-06}]}, {"source": 23, "prod": 0, "target": 14, "value": 3.2615045591151124, "supply": [{"l": "Motor Gasoline", "v": 0.17765424916406186}, {"l": "Gas-Diesel oil", "v": 2.9365674156404515}, {"l": "Natural gas (including LNG)", "v": 0.13210248244837955}, {"l": "Fuel oil", "v": 0.0047651252597451189}, {"l": "Liquefied petroleum gas (LPG)", "v": 0.0073722115603604525}, {"l": "Coal", "v": 0.0030430750421144574}]}, {"source": 23, "prod": 0, "target": 13, "value": 0.25142746098378094, "supply": [{"l": "Motor Gasoline", "v": 0.013695261187192338}, {"l": "Gas-Diesel oil", "v": 0.22637824842486234}, {"l": "Natural gas (including LNG)", "v": 0.010183702383252835}, {"l": "Fuel oil", "v": 0.00036734069311019154}, {"l": "Liquefied petroleum gas (LPG)", "v": 0.00056831943689191269}, {"l": "Coal", "v": 0.00023458885847135996}]}, {"source": 23, "prod": 0, "target": 2, "value": 0.45873620898345419, "supply": [{"l": "Motor Gasoline", "v": 0.024987374781850598}, {"l": "Gas-Diesel oil", "v": 0.41303324255990859}, {"l": "Natural gas (including LNG)", "v": 0.01858044068229496}, {"l": "Fuel oil", "v": 0.00067022303889706825}, {"l": "Liquefied petroleum gas (LPG)", "v": 0.0010369141976429744}, {"l": "Coal", "v": 0.00042801372286000892}]}, {"source": 23, "prod": 0, "target": 3, "value": 0.0063963933322683996, "supply": [{"l": "Motor Gasoline", "v": 0.00034841173274657606}, {"l": "Gas-Diesel oil", "v": 0.0057591335215718392}, {"l": "Natural gas (including LNG)", "v": 0.0002590765772647492}, {"l": "Fuel oil", "v": 9.345262251335595e-06}, {"l": "Liquefied petroleum gas (LPG)", "v": 1.4458224421907757e-05}, {"l": "Coal", "v": 5.9680140119915439e-06}]}, {"source": 23, "prod": 0, "target": 11, "value": 0.03739429948095372, "supply": [{"l": "Motor Gasoline", "v": 0.0020368685914415215}, {"l": "Gas-Diesel oil", "v": 0.033668780587650757}, {"l": "Natural gas (including LNG)", "v": 0.0015146015286246874}, {"l": "Fuel oil", "v": 5.4633840853961942e-05}, {"l": "Liquefied petroleum gas (LPG)", "v": 8.4525004312691502e-05}, {"l": "Coal", "v": 3.4889928070104407e-05}]}, {"source": 23, "prod": 0, "target": 21, "value": 0.065604034177111789, "supply": [{"l": "Motor Gasoline", "v": 0.0035734536691956523}, {"l": "Gas-Diesel oil", "v": 0.059068036118685538}, {"l": "Natural gas (including LNG)", "v": 0.0026571956642538379}, {"l": "Fuel oil", "v": 9.5848843603442007e-05}, {"l": "Liquefied petroleum gas (LPG)", "v": 0.00014828948125033596}, {"l": "Coal", "v": 6.1210400122990193e-05}]}, {"source": 23, "prod": 0, "target": 15, "value": 0.037886329737282058, "supply": [{"l": "Motor Gasoline", "v": 0.002063669493960489}, {"l": "Gas-Diesel oil", "v": 0.034111790858540894}, {"l": "Natural gas (including LNG)", "v": 0.0015345304961065912}, {"l": "Fuel oil", "v": 5.5352707180987754e-05}, {"l": "Liquefied petroleum gas (LPG)", "v": 8.5637175422069022e-05}, {"l": "Coal", "v": 3.5349006071026836e-05}]}, {"source": 23, "prod": 0, "target": 4, "value": 0.71016366996723512, "supply": [{"l": "Motor Gasoline", "v": 0.038682635969042936}, {"l": "Gas-Diesel oil", "v": 0.6394114909847709}, {"l": "Natural gas (including LNG)", "v": 0.028764143065547795}, {"l": "Fuel oil", "v": 0.0010375637320072597}, {"l": "Liquefied petroleum gas (LPG)", "v": 0.0016052336345348868}, {"l": "Coal", "v": 0.00066260258133136888}]}, {"source": 23, "prod": 0, "target": 17, "value": 1.0129262876946059, "supply": [{"l": "Motor Gasoline", "v": 0.055174124652380863}, {"l": "Gas-Diesel oil", "v": 0.91201047767250465}, {"l": "Natural gas (including LNG)", "v": 0.041027101056079249}, {"l": "Fuel oil", "v": 0.0014799061452371444}, {"l": "Liquefied petroleum gas (LPG)", "v": 0.0022895895905051871}, {"l": "Coal", "v": 0.00094508857789896855}]}, {"source": 23, "prod": 0, "target": 19, "value": 0.047562924778406047, "supply": [{"l": "Motor Gasoline", "v": 0.002590753910166848}, {"l": "Gas-Diesel oil", "v": 0.042824326186047014}, {"l": "Natural gas (including LNG)", "v": 0.0019264668565840326}, {"l": "Fuel oil", "v": 6.9490411612495458e-05}, {"l": "Liquefied petroleum gas (LPG)", "v": 0.00010750987390649359}, {"l": "Coal", "v": 4.4377540089167893e-05}]}, {"source": 23, "prod": 0, "target": 12, "value": 0.0082005042721389736, "supply": [{"l": "Motor Gasoline", "v": 0.00044668170864945654}, {"l": "Gas-Diesel oil", "v": 0.0073835045148356922}, {"l": "Natural gas (including LNG)", "v": 0.00033214945803172974}, {"l": "Fuel oil", "v": 1.1981105450430251e-05}, {"l": "Liquefied petroleum gas (LPG)", "v": 1.8536185156291995e-05}, {"l": "Coal", "v": 7.6513000153737741e-06}]}, {"source": 23, "prod": 0, "target": 20, "value": 0.05346728785434611, "supply": [{"l": "Motor Gasoline", "v": 0.0029123647403944569}, {"l": "Gas-Diesel oil", "v": 0.048140449436728718}, {"l": "Natural gas (including LNG)", "v": 0.002165614466366878}, {"l": "Fuel oil", "v": 7.8116807536805243e-05}, {"l": "Liquefied petroleum gas (LPG)", "v": 0.00012085592721902382}, {"l": "Coal", "v": 4.988647610023701e-05}]}, {"source": 23, "prod": 0, "target": 18, "value": 0.050187086145490521, "supply": [{"l": "Motor Gasoline", "v": 0.0027336920569346742}, {"l": "Gas-Diesel oil", "v": 0.045187047630794439}, {"l": "Natural gas (including LNG)", "v": 0.0020327546831541859}, {"l": "Fuel oil", "v": 7.3324365356633136e-05}, {"l": "Liquefied petroleum gas (LPG)", "v": 0.00011344145315650702}, {"l": "Coal", "v": 4.68259560940875e-05}]}, {"source": 23, "prod": 0, "target": 5, "value": 0.082825093148603632, "supply": [{"l": "Motor Gasoline", "v": 0.0045114852573595113}, {"l": "Gas-Diesel oil", "v": 0.074573395599840497}, {"l": "Natural gas (including LNG)", "v": 0.0033547095261204705}, {"l": "Fuel oil", "v": 0.00012100916504934554}, {"l": "Liquefied petroleum gas (LPG)", "v": 0.00018721547007854915}, {"l": "Coal", "v": 7.7278130155275122e-05}]}, {"source": 23, "prod": 0, "target": 16, "value": 0.10037417229098104, "supply": [{"l": "Motor Gasoline", "v": 0.0054673841138693485}, {"l": "Gas-Diesel oil", "v": 0.090374095261588877}, {"l": "Natural gas (including LNG)", "v": 0.0040655093663083718}, {"l": "Fuel oil", "v": 0.00014664873071326627}, {"l": "Liquefied petroleum gas (LPG)", "v": 0.00022688290631301403}, {"l": "Coal", "v": 9.3651912188175e-05}]}, {"source": 25, "prod": 0.87021971686631228, "target": 6, "value": 0.0082417416441376689, "supply": [{"l": "Potash", "v": 0.94607500075686002}, {"l": "Phosphate", "v": 0.41999166700266}, {"l": "Nitrogen", "v": 6.3536430606384693}]}, {"source": 25, "prod": 5.2039139068605467, "target": 0, "value": 0.049285615031943258, "supply": [{"l": "Potash", "v": 0.94607500075686002}, {"l": "Phosphate", "v": 0.41999166700266}, {"l": "Nitrogen", "v": 6.3536430606384693}]}, {"source": 25, "prod": 58.130677086669664, "target": 10, "value": 0.55054834182839629, "supply": [{"l": "Potash", "v": 0.94607500075686002}, {"l": "Phosphate", "v": 0.41999166700266}, {"l": "Nitrogen", "v": 6.3536430606384693}]}, {"source": 25, "prod": 46.870033950419575, "target": 8, "value": 0.44390020495325483, "supply": [{"l": "Potash", "v": 0.94607500075686002}, {"l": "Phosphate", "v": 0.41999166700266}, {"l": "Nitrogen", "v": 6.3536430606384693}]}, {"source": 25, "prod": 43.824264941387483, "target": 7, "value": 0.415054109198773, "supply": [{"l": "Potash", "v": 0.94607500075686002}, {"l": "Phosphate", "v": 0.41999166700266}, {"l": "Nitrogen", "v": 6.3536430606384693}]}, {"source": 25, "prod": 0.6787713791557235, "target": 9, "value": 0.006428558482427381, "supply": [{"l": "Potash", "v": 0.94607500075686002}, {"l": "Phosphate", "v": 0.41999166700266}, {"l": "Nitrogen", "v": 6.3536430606384693}]}, {"source": 25, "prod": 346.10378579206969, "target": 14, "value": 3.2779054867064334, "supply": [{"l": "Potash", "v": 0.94607500075686002}, {"l": "Phosphate", "v": 0.41999166700266}, {"l": "Nitrogen", "v": 6.3536430606384693}]}, {"source": 25, "prod": 26.680936519121136, "target": 13, "value": 0.25269179880926096, "supply": [{"l": "Potash", "v": 0.94607500075686002}, {"l": "Phosphate", "v": 0.41999166700266}, {"l": "Nitrogen", "v": 6.3536430606384693}]}, {"source": 25, "prod": 48.680090961501506, "target": 2, "value": 0.4610430275730612, "supply": [{"l": "Potash", "v": 0.94607500075686002}, {"l": "Phosphate", "v": 0.41999166700266}, {"l": "Nitrogen", "v": 6.3536430606384693}]}, {"source": 25, "prod": 0.6787713791557235, "target": 3, "value": 0.006428558482427381, "supply": [{"l": "Potash", "v": 0.94607500075686002}, {"l": "Phosphate", "v": 0.41999166700266}, {"l": "Nitrogen", "v": 6.3536430606384693}]}, {"source": 25, "prod": 3.9682019089103835, "target": 11, "value": 0.037582341897267765, "supply": [{"l": "Potash", "v": 0.94607500075686002}, {"l": "Phosphate", "v": 0.41999166700266}, {"l": "Nitrogen", "v": 6.3536430606384693}]}, {"source": 25, "prod": 6.9617577349304982, "target": 21, "value": 0.065933933153101351, "supply": [{"l": "Potash", "v": 0.94607500075686002}, {"l": "Phosphate", "v": 0.41999166700266}, {"l": "Nitrogen", "v": 6.3536430606384693}]}, {"source": 25, "prod": 4.020415091922362, "target": 15, "value": 0.038076846395916027, "supply": [{"l": "Potash", "v": 0.94607500075686002}, {"l": "Phosphate", "v": 0.41999166700266}, {"l": "Nitrogen", "v": 6.3536430606384693}]}, {"source": 25, "prod": 75.361027480622639, "target": 4, "value": 0.71373482638232211, "supply": [{"l": "Potash", "v": 0.94607500075686002}, {"l": "Phosphate", "v": 0.41999166700266}, {"l": "Nitrogen", "v": 6.3536430606384693}]}, {"source": 25, "prod": 107.48953942732687, "target": 17, "value": 1.0180199278838848, "supply": [{"l": "Potash", "v": 0.94607500075686002}, {"l": "Phosphate", "v": 0.41999166700266}, {"l": "Nitrogen", "v": 6.3536430606384693}]}, {"source": 25, "prod": 5.0472743578246115, "target": 19, "value": 0.047802101535998481, "supply": [{"l": "Potash", "v": 0.94607500075686002}, {"l": "Phosphate", "v": 0.41999166700266}, {"l": "Nitrogen", "v": 6.3536430606384693}]}, {"source": 25, "prod": 0.87021971686631228, "target": 12, "value": 0.0082417416441376689, "supply": [{"l": "Potash", "v": 0.94607500075686002}, {"l": "Phosphate", "v": 0.41999166700266}, {"l": "Nitrogen", "v": 6.3536430606384693}]}, {"source": 25, "prod": 5.6738325539683565, "target": 20, "value": 0.053736155519777604, "supply": [{"l": "Potash", "v": 0.94607500075686002}, {"l": "Phosphate", "v": 0.41999166700266}, {"l": "Nitrogen", "v": 6.3536430606384693}]}, {"source": 25, "prod": 5.3257446672218309, "target": 18, "value": 0.050439458862122533, "supply": [{"l": "Potash", "v": 0.94607500075686002}, {"l": "Phosphate", "v": 0.41999166700266}, {"l": "Nitrogen", "v": 6.3536430606384693}]}, {"source": 25, "prod": 8.7892191403497542, "target": 5, "value": 0.083241590605790464, "supply": [{"l": "Potash", "v": 0.94607500075686002}, {"l": "Phosphate", "v": 0.41999166700266}, {"l": "Nitrogen", "v": 6.3536430606384693}]}, {"source": 25, "prod": 10.651489334443662, "target": 16, "value": 0.10087891772424507, "supply": [{"l": "Potash", "v": 0.94607500075686002}, {"l": "Phosphate", "v": 0.41999166700266}, {"l": "Nitrogen", "v": 6.3536430606384693}]}, {"source": 23, "prod": 0, "target": 25, "value": 10.06417984439938, "supply": [{"l": "Natural gas (including LNG)", "v": 6.4984051837003349}, {"l": "Fuel oil", "v": 2.4426336386494021}, {"l": "Liquefied petroleum gas (LPG)", "v": 0.56157051102482136}, {"l": "Coal", "v": 0.56157051102482136}]}, {"source": 26, "prod": 0, "target": 6, "value": 0.00045725334628590904, "supply": "[{\"l\":'Labor',\"v\":0.00045725334628590904}]"}, {"source": 26, "prod": 0, "target": 0, "value": 0.0027343750107897361, "supply": "[{\"l\":'Labor',\"v\":0.0027343750107897361}]"}, {"source": 26, "prod": 0, "target": 10, "value": 0.030544523531898727, "supply": "[{\"l\":'Labor',\"v\":0.030544523531898727}]"}, {"source": 26, "prod": 0, "target": 8, "value": 0.024627665230959061, "supply": "[{\"l\":'Labor',\"v\":0.024627665230959061}]"}, {"source": 26, "prod": 0, "target": 7, "value": 0.023027278518958378, "supply": "[{\"l\":'Labor',\"v\":0.023027278518958378}]"}, {"source": 26, "prod": 0, "target": 9, "value": 0.00035665761010300904, "supply": "[{\"l\":'Labor',\"v\":0.00035665761010300904}]"}, {"source": 26, "prod": 0, "target": 14, "value": 0.18185880088483175, "supply": "[{\"l\":'Labor',\"v\":0.18185880088483175}]"}, {"source": 26, "prod": 0, "target": 13, "value": 0.014019387597125973, "supply": "[{\"l\":'Labor',\"v\":0.014019387597125973}]"}, {"source": 26, "prod": 0, "target": 2, "value": 0.025578752191233751, "supply": "[{\"l\":'Labor',\"v\":0.025578752191233751}]"}, {"source": 26, "prod": 0, "target": 3, "value": 0.00035665761010300904, "supply": "[{\"l\":'Labor',\"v\":0.00035665761010300904}]"}, {"source": 26, "prod": 0, "target": 11, "value": 0.0020850752590637453, "supply": "[{\"l\":'Labor',\"v\":0.0020850752590637453}]"}, {"source": 26, "prod": 0, "target": 21, "value": 0.0036580267702872723, "supply": "[{\"l\":'Labor',\"v\":0.0036580267702872723}]"}, {"source": 26, "prod": 0, "target": 15, "value": 0.0021125104598408999, "supply": "[{\"l\":'Labor',\"v\":0.0021125104598408999}]"}, {"source": 26, "prod": 0, "target": 4, "value": 0.039598139788359722, "supply": "[{\"l\":'Labor',\"v\":0.039598139788359722}]"}, {"source": 26, "prod": 0, "target": 17, "value": 0.056479933333235477, "supply": "[{\"l\":'Labor',\"v\":0.056479933333235477}]"}, {"source": 26, "prod": 0, "target": 19, "value": 0.0026520694084582728, "supply": "[{\"l\":'Labor',\"v\":0.0026520694084582728}]"}, {"source": 26, "prod": 0, "target": 12, "value": 0.00045725334628590904, "supply": "[{\"l\":'Labor',\"v\":0.00045725334628590904}]"}, {"source": 26, "prod": 0, "target": 20, "value": 0.0029812918177841274, "supply": "[{\"l\":'Labor',\"v\":0.0029812918177841274}]"}, {"source": 26, "prod": 0, "target": 18, "value": 0.0027983904792697636, "supply": "[{\"l\":'Labor',\"v\":0.0027983904792697636}]"}, {"source": 26, "prod": 0, "target": 5, "value": 0.004618258797487681, "supply": "[{\"l\":'Labor',\"v\":0.004618258797487681}]"}, {"source": 26, "prod": 0, "target": 16, "value": 0.0055967809585395272, "supply": "[{\"l\":'Labor',\"v\":0.0055967809585395272}]"}]}